spice21py-0.1.5.dist-info/METADATA
spice21py-0.1.5.dist-info/WHEEL
spice21py/protos/bsim4_pb2.py
spice21py/protos/mos_pb2.py
spice21py/protos/__init__.py
spice21py/protos/spice21_pb2.py
spice21py/protos/__pycache__/__init__.cpython-38.pyc
spice21py/protos/__pycache__/spice21_pb2.cpython-38.pyc
spice21py/protos/__pycache__/bsim4_pb2.cpython-38.pyc
spice21py/protos/__pycache__/mos_pb2.cpython-38.pyc
spice21py/tests/__init__.py
spice21py/tests/__pycache__/__init__.cpython-38.pyc
spice21py/tests/__pycache__/test_spice21.cpython-38-pytest-6.0.1.pyc
spice21py/tests/__pycache__/test_spice21.cpython-38-pytest-6.1.1.pyc
spice21py/tests/test_spice21.py
spice21py/__init__.py
spice21py/__pycache__/protos.cpython-38.pyc
spice21py/__pycache__/__init__.cpython-38.pyc
spice21py/__pycache__/spice21_pb2.cpython-38.pyc
spice21py/__pycache__/bsim4_pb2.cpython-38.pyc
spice21py/__pycache__/mos_pb2.cpython-38.pyc
spice21py/spice21py.cpython-38-darwin.so
spice21py-0.1.5.dist-info/RECORD
